unidata_blocks/__init__.py
unidata_blocks/unidata/Blocks.txt
unidata_blocks/unidata/translations/zh-Hans.txt
unidata_blocks/unidata/translations/zh-Hant.txt
unidata_blocks-0.0.24.dist-info/WHEEL
unidata_blocks-0.0.24.dist-info/METADATA
unidata_blocks-0.0.24.dist-info/RECORD
