Metadata-Version: 2.4
Name: unidata-blocks
Version: 0.0.24
Summary: A library that helps query Unicode blocks by Blocks.txt
Keywords: unicode
Author: TakWolf
License-Expression: MIT
Classifier: Programming Language :: Python :: 3
Classifier: Programming Language :: Python :: 3.10
Classifier: Programming Language :: Python :: 3.11
Classifier: Programming Language :: Python :: 3.12
Classifier: Programming Language :: Python :: 3.13
Classifier: Programming Language :: Python :: 3.14
Classifier: License :: OSI Approved :: MIT License
Classifier: Operating System :: OS Independent
Requires-Dist: langcodes>=3.5.0
Maintainer: TakWolf
Requires-Python: >=3.10
Project-URL: Homepage, https://github.com/TakWolf/unidata-blocks
Project-URL: Issues, https://github.com/TakWolf/unidata-blocks/issues
Project-URL: Source, https://github.com/TakWolf/unidata-blocks
